odoo9_addon_stock_location_lockdown-9.0.1.0.0.99.dev4-nspkg.pth
odoo_addons/stock_location_lockdown/README.rst
odoo_addons/stock_location_lockdown/__init__.py
odoo_addons/stock_location_lockdown/__openerp__.py
odoo_addons/stock_location_lockdown/i18n/fr.po
odoo_addons/stock_location_lockdown/i18n/stock_location_lockdown.pot
odoo_addons/stock_location_lockdown/models/__init__.py
odoo_addons/stock_location_lockdown/models/stock_location.py
odoo_addons/stock_location_lockdown/models/stock_quant.py
odoo_addons/stock_location_lockdown/readme/CONTRIBUTORS.rst
odoo_addons/stock_location_lockdown/readme/DESCRIPTION.rst
odoo_addons/stock_location_lockdown/readme/USAGE.rst
odoo_addons/stock_location_lockdown/static/description/icon.png
odoo_addons/stock_location_lockdown/static/description/index.html
odoo_addons/stock_location_lockdown/tests/__init__.py
odoo_addons/stock_location_lockdown/tests/test_block_stock_location_entrance.py
odoo_addons/stock_location_lockdown/views/stock_location.xml
odoo9_addon_stock_location_lockdown-9.0.1.0.0.99.dev4.dist-info/METADATA
odoo9_addon_stock_location_lockdown-9.0.1.0.0.99.dev4.dist-info/WHEEL
odoo9_addon_stock_location_lockdown-9.0.1.0.0.99.dev4.dist-info/namespace_packages.txt
odoo9_addon_stock_location_lockdown-9.0.1.0.0.99.dev4.dist-info/top_level.txt
odoo9_addon_stock_location_lockdown-9.0.1.0.0.99.dev4.dist-info/RECORD
